mongodb_connect/__init__.py
mongodb_connect/mysql_crud.py
awsrds_crud_wenboliu-0.1.0.dist-info/LICENSE
awsrds_crud_wenboliu-0.1.0.dist-info/METADATA
awsrds_crud_wenboliu-0.1.0.dist-info/WHEEL
awsrds_crud_wenboliu-0.1.0.dist-info/top_level.txt
awsrds_crud_wenboliu-0.1.0.dist-info/RECORD
